vuln2vec/CBKeywords_mapping.json
vuln2vec/__init__.py
vuln2vec/preprocessor.py
vuln2vec-1.1.0.dist-info/LICENSE
vuln2vec-1.1.0.dist-info/METADATA
vuln2vec-1.1.0.dist-info/WHEEL
vuln2vec-1.1.0.dist-info/top_level.txt
vuln2vec-1.1.0.dist-info/RECORD
