Metadata-Version: 2.1
Name: vuln2vec
Version: 1.1.0
License-File: LICENSE
Requires-Dist: flashtext
Requires-Dist: gensim==4.3.3
Requires-Dist: numpy==1.26.4
